zebra/__init__.py
zebra/py.typed
zebra/zebra.pyi
zebra-0.2.1.dist-info/METADATA
zebra-0.2.1.dist-info/WHEEL
zebra-0.2.1.dist-info/licenses/LICENCE
zebra-0.2.1.dist-info/RECORD
