Metadata-Version: 2.4
Name: zebra
Version: 0.2.1
Summary: A package to communicate with (Zebra) label printers
Project-URL: homepage, https://www.wyre-it.co.uk/zebra/
Author-email: Ben Croston <ben@croston.org>
Maintainer-email: Ben Croston <ben@croston.org>
License-Expression: MIT
License-File: LICENCE
Classifier: Development Status :: 5 - Production/Stable
Classifier: Intended Audience :: Developers
Classifier: License :: OSI Approved :: MIT License
Classifier: Operating System :: MacOS :: MacOS X
Classifier: Operating System :: Microsoft :: Windows
Classifier: Operating System :: Unix
Classifier: Programming Language :: Python :: 3
Classifier: Topic :: Printing
Requires-Python: >=3.8
Requires-Dist: pywin32; platform_system == 'Windows'
